{
  "config": {
    "dates": [
      "8.25",
      "8.26"
    ],
    "times": [
      "上午",
      "下午",
      "晚上"
    ],
    "activities": [
      "电影",
      "k歌"
    ],
    "foods": [
      "火锅",
      "漂亮饭",
      "烤肉"
    ],
    "yourName": "Lester",
    "herName": "亲爱的weining",
    "inviteMessage": "宝贝，我想你了"
  },
  "response": {
    "selectedDate": "8.25",
    "selectedTime": "上午",
    "selectedActivity": "k歌",
    "selectedFood": "火锅",
    "note": "爱你",
    "submittedAt": "2026-07-11T12:28:39.337Z"
  }
}